module/__init__.py
module/playwright_utils.py
odc_playwright_utils-0.1.0.dist-info/LICENSE
odc_playwright_utils-0.1.0.dist-info/METADATA
odc_playwright_utils-0.1.0.dist-info/WHEEL
odc_playwright_utils-0.1.0.dist-info/top_level.txt
odc_playwright_utils-0.1.0.dist-info/RECORD
