Metadata-Version: 2.1
Name: odc-playwright-utils
Version: 0.1.0
Summary: A set of utility functions for Playwright-based UI automation
Author: Your Name
Author-email: qym00725@163.com
Classifier: Programming Language :: Python :: 3
Classifier: License :: OSI Approved :: MIT License
Classifier: Operating System :: OS Independent
Requires-Python: >=3.6
License-File: LICENSE
Requires-Dist: playwright ==1.45.1
